odoo/addons/l10n_eu_product_adr/README.rst
odoo/addons/l10n_eu_product_adr/__init__.py
odoo/addons/l10n_eu_product_adr/__manifest__.py
odoo/addons/l10n_eu_product_adr/data/product_dangerous_class_data.xml
odoo/addons/l10n_eu_product_adr/data/product_dangerous_type_data.xml
odoo/addons/l10n_eu_product_adr/data/utility_models_data.xml
odoo/addons/l10n_eu_product_adr/i18n/de.po
odoo/addons/l10n_eu_product_adr/i18n/l10n_eu_product_adr.pot
odoo/addons/l10n_eu_product_adr/i18n/nl.po
odoo/addons/l10n_eu_product_adr/models/__init__.py
odoo/addons/l10n_eu_product_adr/models/product_dangerous.py
odoo/addons/l10n_eu_product_adr/models/product_product.py
odoo/addons/l10n_eu_product_adr/models/utility_models.py
odoo/addons/l10n_eu_product_adr/readme/AUTHORS.rst
odoo/addons/l10n_eu_product_adr/readme/DESCRIPTION.rst
odoo/addons/l10n_eu_product_adr/readme/ROADMAP.rst
odoo/addons/l10n_eu_product_adr/security/ir.model.access.csv
odoo/addons/l10n_eu_product_adr/static/description/icon.png
odoo/addons/l10n_eu_product_adr/static/description/index.html
odoo/addons/l10n_eu_product_adr/static/img/ADR_1.svg
odoo/addons/l10n_eu_product_adr/static/img/ADR_2.1.svg
odoo/addons/l10n_eu_product_adr/static/img/ADR_2.2.svg
odoo/addons/l10n_eu_product_adr/static/img/ADR_2.3.svg
odoo/addons/l10n_eu_product_adr/static/img/ADR_3.svg
odoo/addons/l10n_eu_product_adr/static/img/ADR_4.1.svg
odoo/addons/l10n_eu_product_adr/static/img/ADR_4.2.svg
odoo/addons/l10n_eu_product_adr/static/img/ADR_4.3.svg
odoo/addons/l10n_eu_product_adr/static/img/ADR_5.1.svg
odoo/addons/l10n_eu_product_adr/static/img/ADR_5.2.svg
odoo/addons/l10n_eu_product_adr/static/img/ADR_6.2.svg
odoo/addons/l10n_eu_product_adr/static/img/ADR_7B.svg
odoo/addons/l10n_eu_product_adr/static/img/ADR_9.svg
odoo/addons/l10n_eu_product_adr/static/img/ADR_9A.svg
odoo/addons/l10n_eu_product_adr/static/img/Dangclass6_1.svg
odoo/addons/l10n_eu_product_adr/static/img/UN_transport_pictogram_-_8.svg
odoo13_addon_l10n_eu_product_adr-13.0.2.1.0.dist-info/METADATA
odoo13_addon_l10n_eu_product_adr-13.0.2.1.0.dist-info/WHEEL
odoo13_addon_l10n_eu_product_adr-13.0.2.1.0.dist-info/top_level.txt
odoo13_addon_l10n_eu_product_adr-13.0.2.1.0.dist-info/RECORD
